LIM/LIM.py
LIM/__init__.py
LIM/__main__.py
LIM_cpu-1.0.2.dist-info/LICENSE.md
LIM_cpu-1.0.2.dist-info/METADATA
LIM_cpu-1.0.2.dist-info/WHEEL
LIM_cpu-1.0.2.dist-info/entry_points.txt
LIM_cpu-1.0.2.dist-info/top_level.txt
LIM_cpu-1.0.2.dist-info/RECORD
