Metadata-Version: 2.1
Name: LIM-cpu
Version: 1.0.2
Summary: Simple command line app for converting asm files to bin files for the LIM cpu
Home-page: https://github.com/Spud304/LIM-Assembler
Author: Henry Price
Author-email: hcprice115@gmail.com
License: MIT
Download-URL: https://github.com/Spud304/LIM-Assembler/archive/1.0.6.tar.gz
Platform: UNKNOWN
Classifier: License :: OSI Approved :: MIT License
Classifier: Programming Language :: Python :: 3
Classifier: Programming Language :: Python :: 3.9
Requires-Python: >=3.9
